{
  "id": "ADL_scale",
  "gdl_version": "2.0",
  "concept": "gt0001",
  "language": {
    "original_language": "ISO_639-1::en"
  },
  "description": {
    "original_author": {
      "date": "2019-07-30",
      "name": "Blanca Flores",
      "organisation": "Institute of Medical Biometry and Informatics",
      "email": "blanca.flores@med.uni-heidelberg.de"
    },
    "lifecycle_state": "Not set",
    "details": {
      "en": {
        "id": "en",
        "purpose": "To assess functional status as a measurement of the elder´s ability to perform activities of daily living independently. ",
        "keywords": [
          "Geriatric assessment",
          "ADL scale"
        ],
        "use": "Use to assess functional status in elderly and calculate a total ADL score.",
        "misuse": "Do not use to assess other activities than the specified by the ADL scale. "
      }
    },
    "other_details": {
      "references": "Katz S., Ford AB, Moskowitz RW, et al. Studies of Illness in the Aged. The Index of ADL: A Standardized Measure of Biological and Psychosocial Function. JAMA: 1963; 185(12):914-919. "
    }
  },
  "definition": {
    "data_bindings": {
      "gt0002": {
        "id": "gt0002",
        "model_id": "openEHR-EHR-OBSERVATION.katz_activity_of_daily_living.v0",
        "template_id": "openEHR-EHR-OBSERVATION.katz_activity_of_daily_living.v0",
        "type": "INPUT",
        "elements": {
          "gt0003": {
            "id": "gt0003",
            "path": "/data[at0001]/events[at0002]/data[at0003]/items[at0007]"
          },
          "gt0004": {
            "id": "gt0004",
            "path": "/data[at0001]/events[at0002]/data[at0003]/items[at0010]"
          },
          "gt0005": {
            "id": "gt0005",
            "path": "/data[at0001]/events[at0002]/data[at0003]/items[at0013]"
          },
          "gt0006": {
            "id": "gt0006",
            "path": "/data[at0001]/events[at0002]/data[at0003]/items[at0016]"
          },
          "gt0007": {
            "id": "gt0007",
            "path": "/data[at0001]/events[at0002]/data[at0003]/items[at0019]"
          },
          "gt0008": {
            "id": "gt0008",
            "path": "/data[at0001]/events[at0002]/data[at0003]/items[at0004]"
          },
          "gt0028": {
            "id": "gt0028",
            "path": "/data/events/time"
          }
        }
      },
      "gt0013": {
        "id": "gt0013",
        "model_id": "openEHR-EHR-OBSERVATION.adl_score.v0",
        "template_id": "openEHR-EHR-OBSERVATION.adl_score.v0",
        "type": "OUTPUT",
        "elements": {
          "gt0014": {
            "id": "gt0014",
            "path": "/data[at0001]/events[at0002]/data[at0003]/items[at0004]"
          },
          "gt0015": {
            "id": "gt0015",
            "path": "/data[at0001]/events[at0002]/data[at0003]/items[at0005]"
          },
          "gt0016": {
            "id": "gt0016",
            "path": "/data[at0001]/events[at0002]/data[at0003]/items[at0006]"
          },
          "gt0017": {
            "id": "gt0017",
            "path": "/data[at0001]/events[at0002]/data[at0003]/items[at0009]"
          },
          "gt0018": {
            "id": "gt0018",
            "path": "/data[at0001]/events[at0002]/data[at0003]/items[at0007]"
          },
          "gt0019": {
            "id": "gt0019",
            "path": "/data[at0001]/events[at0002]/data[at0003]/items[at0008]"
          },
          "gt0020": {
            "id": "gt0020",
            "path": "/data[at0001]/events[at0002]/data[at0003]/items[at0010]"
          }
        }
      }
    },
    "rules": {
      "gt0021": {
        "id": "gt0021",
        "priority": 8,
        "when": [
          "$gt0019|Feeding points|==null",
          "$gt0018|Continence points|==null",
          "$gt0017|Transferring points|==null",
          "$gt0016|Toileting points|==null",
          "$gt0015|Dressing points|==null",
          "$gt0014|Bathing points|==null"
        ],
        "then": [
          "$gt0019|Feeding points|=0",
          "$gt0018|Continence points|=0",
          "$gt0017|Transferring points|=0",
          "$gt0016|Toileting points|=0",
          "$gt0015|Dressing points|=0",
          "$gt0014|Bathing points|=0"
        ]
      },
      "gt0012": {
        "id": "gt0012",
        "priority": 7,
        "when": [
          "$gt0003|Bathing|==1|local::at0009|Bathes self completely or needs help in bathing only a single part of the body such as the back, genital area or disabled extremity. |"
        ],
        "then": [
          "$gt0014|Bathing points|=1"
        ]
      },
      "gt0023": {
        "id": "gt0023",
        "priority": 6,
        "when": [
          "$gt0004|Dressing|==1|local::at0012|Gets clothes from closets and drawers and puts on clothes and outer garments complete with fasteners. May have help tying shoes.|"
        ],
        "then": [
          "$gt0015|Dressing points|=1"
        ]
      },
      "gt0024": {
        "id": "gt0024",
        "priority": 5,
        "when": [
          "$gt0005|Toileting|==1|local::at0015|Goes to toilet, gets on and off, arranges clothes, cleans genital area without help.|"
        ],
        "then": [
          "$gt0016|Toileting points|=1"
        ]
      },
      "gt0027": {
        "id": "gt0027",
        "priority": 4,
        "when": [
          "$gt0008|Feeding|==1|local::at0006|Gets food from plate into mouth without help. Preparation of food may be done by another person.|"
        ],
        "then": [
          "$gt0019|Feeding points|=1"
        ]
      },
      "gt0025": {
        "id": "gt0025",
        "priority": 3,
        "when": [
          "$gt0006|Transferring|==1|local::at0018|Moves in and out of bed or chair unassisted. Mechanical transferring aides are acceptable.|"
        ],
        "then": [
          "$gt0017|Transferring points|=1"
        ]
      },
      "gt0026": {
        "id": "gt0026",
        "priority": 2,
        "when": [
          "$gt0007|Continence|==1|local::at0021|Exercises complete self control over urination and defecation. |"
        ],
        "then": [
          "$gt0018|Continence points|=1"
        ]
      },
      "gt0030": {
        "id": "gt0030",
        "priority": 1,
        "when": [
          "$gt0003|Bathing|!=null",
          "$gt0004|Dressing|!=null",
          "$gt0005|Toileting|!=null",
          "$gt0006|Transferring|!=null",
          "$gt0007|Continence|!=null",
          "$gt0008|Feeding|!=null"
        ],
        "then": [
          "$gt0020|Total ADL score|.magnitude=$gt0014+$gt0015+$gt0016+$gt0017+$gt0018+$gt0019"
        ]
      }
    }
  },
  "ontology": {
    "term_definitions": {
      "en": {
        "id": "en",
        "terms": {
          "gt0001": {
            "id": "gt0001",
            "text": "ADL_scale",
            "description": "The Katz Activity of Daily Living (ADL) scale assesses the level of independency in elderly, based on six items (bathing, dressing, toileting, transferring, continence and feeding). The score for each item ranges from 0 (unable to perform the activity) to 1 (able to perform the activity). The total ADL score ranges from 0 (completely dependent) to 6 (completely independent)."
          },
          "gt0003": {
            "id": "gt0003",
            "text": "Bathing",
            "description": "*"
          },
          "gt0004": {
            "id": "gt0004",
            "text": "Dressing",
            "description": "*"
          },
          "gt0005": {
            "id": "gt0005",
            "text": "Toileting",
            "description": "*"
          },
          "gt0006": {
            "id": "gt0006",
            "text": "Transferring",
            "description": "*"
          },
          "gt0007": {
            "id": "gt0007",
            "text": "Continence",
            "description": "*"
          },
          "gt0008": {
            "id": "gt0008",
            "text": "Feeding",
            "description": "*"
          },
          "gt0009": {
            "id": "gt0009",
            "text": "Total score",
            "description": "*"
          },
          "gt0011": {
            "id": "gt0011",
            "text": "Total score",
            "description": "*"
          },
          "gt0012": {
            "id": "gt0012",
            "text": "Bathing score"
          },
          "gt0014": {
            "id": "gt0014",
            "text": "Bathing points",
            "description": "*"
          },
          "gt0015": {
            "id": "gt0015",
            "text": "Dressing points",
            "description": "*"
          },
          "gt0016": {
            "id": "gt0016",
            "text": "Toileting points",
            "description": "*"
          },
          "gt0017": {
            "id": "gt0017",
            "text": "Transferring points",
            "description": "*"
          },
          "gt0018": {
            "id": "gt0018",
            "text": "Continence points",
            "description": "*"
          },
          "gt0019": {
            "id": "gt0019",
            "text": "Feeding points",
            "description": "*"
          },
          "gt0020": {
            "id": "gt0020",
            "text": "Total ADL score",
            "description": "*"
          },
          "gt0021": {
            "id": "gt0021",
            "text": "Set default"
          },
          "gt0022": {
            "id": "gt0022",
            "text": "Calculate ADL score"
          },
          "gt0023": {
            "id": "gt0023",
            "text": "Dressing score"
          },
          "gt0024": {
            "id": "gt0024",
            "text": "Toileting score"
          },
          "gt0025": {
            "id": "gt0025",
            "text": "Transferring score"
          },
          "gt0026": {
            "id": "gt0026",
            "text": "Continence score"
          },
          "gt0027": {
            "id": "gt0027",
            "text": "Feeding score"
          },
          "gt0028": {
            "id": "gt0028",
            "text": "Event time",
            "description": "The exact time of a single timed event during the Observation. Can represent either a specific point-in-time or an interval event."
          },
          "gt0029": {
            "id": "gt0029",
            "text": "Calculate ADL score"
          },
          "gt0030": {
            "id": "gt0030",
            "text": "Calculate ADL score"
          }
        }
      }
    }
  }
}